riscos_disassemble/__init__.py
riscos_disassemble/__main__.py
riscos_disassemble/colours.py
riscos_disassemble/disassemble.py
riscos_disassemble/postprocess.py
riscos_disassemble/swis.py
riscos_disassemble-0.5.0.dist-info/LICENSE
riscos_disassemble-0.5.0.dist-info/METADATA
riscos_disassemble-0.5.0.dist-info/WHEEL
riscos_disassemble-0.5.0.dist-info/entry_points.txt
riscos_disassemble-0.5.0.dist-info/top_level.txt
riscos_disassemble-0.5.0.dist-info/RECORD
