Metadata-Version: 2.1
Name: riscos-disassemble
Version: 0.5.0
Summary: Disassemble ARM and Thumb files like RISC OS
Home-page: https://github.com/gerph/riscos-disassemble-python
Author: Charles Ferguson
Author-email: gerph@gerph.org
License: MIT
Keywords: disassemble,arm,riscos
Platform: UNKNOWN
Classifier: Development Status :: 4 - Beta
Classifier: Intended Audience :: Developers
Classifier: License :: OSI Approved :: MIT License
Classifier: Programming Language :: Python :: 2.7
Classifier: Programming Language :: Python :: 3
Classifier: Operating System :: OS Independent
Requires-Python: >=2.7
Requires-Dist: capstone
